pgEdge_pulumi_pgedge/__init__.py
pgEdge_pulumi_pgedge/_inputs.py
pgEdge_pulumi_pgedge/_utilities.py
pgEdge_pulumi_pgedge/backup_store.py
pgEdge_pulumi_pgedge/cloud_account.py
pgEdge_pulumi_pgedge/cluster.py
pgEdge_pulumi_pgedge/database.py
pgEdge_pulumi_pgedge/get_backup_stores.py
pgEdge_pulumi_pgedge/get_cloud_accounts.py
pgEdge_pulumi_pgedge/get_clusters.py
pgEdge_pulumi_pgedge/get_databases.py
pgEdge_pulumi_pgedge/get_ssh_keys.py
pgEdge_pulumi_pgedge/outputs.py
pgEdge_pulumi_pgedge/provider.py
pgEdge_pulumi_pgedge/py.typed
pgEdge_pulumi_pgedge/ssh_key.py
pgEdge_pulumi_pgedge/config/__init__.py
pgEdge_pulumi_pgedge/config/__init__.pyi
pgEdge_pulumi_pgedge/config/vars.py
pgedge_pulumi_pgedge-0.0.42.dist-info/METADATA
pgedge_pulumi_pgedge-0.0.42.dist-info/WHEEL
pgedge_pulumi_pgedge-0.0.42.dist-info/top_level.txt
pgedge_pulumi_pgedge-0.0.42.dist-info/RECORD
