Metadata-Version: 2.4
Name: pgEdge_pulumi_pgedge
Version: 0.0.42
Requires-Dist: pulumi<4.0.0,>=3.0.0
Dynamic: requires-dist
